LICENSE
README.md
setup.cfg
setup.py
prepare_commit_msg/__init__.py
prepare_commit_msg/hook.py
prepare_commit_msg/template.py
prepare_commit_msg/util.py
prepare_commit_msg.egg-info/PKG-INFO
prepare_commit_msg.egg-info/SOURCES.txt
prepare_commit_msg.egg-info/dependency_links.txt
prepare_commit_msg.egg-info/entry_points.txt
prepare_commit_msg.egg-info/requires.txt
prepare_commit_msg.egg-info/top_level.txt
prepare_commit_msg/templates/__init__.py
prepare_commit_msg/templates/prepare_commit_msg_append.j2
prepare_commit_msg/templates/prepare_commit_msg_prepend.j2
testing/__init__.py
testing/util.py